django_fast_sync
tests
