Metadata-Version: 1.1
Name: django-fast-sync
Version: 0.3.1
Summary: A Django app which helps you to import a lot of data with raw SQL
Home-page: https://github.com/bykof/django-fast-sync
Author: mbykovski
Author-email: mbykovski@seibert-media.net
License: Apache License
Platform: UNKNOWN
Requires: django
